<?xml version="1.0" encoding="UTF-8"?>
<ROWSET>
	<ROW>
		<FIELD1>5</FIELD1>
		<FIELD2>00, 15, 30, 45</FIELD2>
		<FIELD3>00, 30</FIELD3>
		<FIELD4>30</FIELD4>
		<FIELD5>30</FIELD5>
		<TITLE>Noszlopy G. park - Homokbánya kollégium</TITLE>
	</ROW>
	<ROW>
		<FIELD1>6</FIELD1>
		<FIELD2>00, 15, 30, 40, 50</FIELD2>
		<FIELD3>00, 20, 40</FIELD3>
		<FIELD4>30</FIELD4> 
		<FIELD5>30</FIELD5>
	</ROW>
	<ROW>
		<FIELD1>7</FIELD1>
		<FIELD2>00, 10, 20, 30, 45</FIELD2>
		<FIELD3>00, 20, 40</FIELD3>
		<FIELD4>30</FIELD4> 
		<FIELD5>30</FIELD5>
	</ROW>
	<ROW>
		<FIELD1>8</FIELD1>
		<FIELD2>00, 15, 30, 45</FIELD2>
		<FIELD3>00, 30</FIELD3>
		<FIELD4>00, 30</FIELD4> 
		<FIELD5>00, 30</FIELD5>
	</ROW>
	<ROW>
		<FIELD1>9</FIELD1>
		<FIELD2>00, 15, 30, 45</FIELD2>
		<FIELD3>00, 30</FIELD3>
		<FIELD4>00, 30</FIELD4> 
		<FIELD5>00, 30</FIELD5>
	</ROW>
	<ROW>
		<FIELD1>10</FIELD1>
		<FIELD2>00, 15, 30, 45</FIELD2>
		<FIELD3>00, 30</FIELD3>
		<FIELD4>00, 30</FIELD4> 
		<FIELD5>00, 30</FIELD5>
	</ROW>
	<ROW>
		<FIELD1>11</FIELD1>
		<FIELD2>00, 15, 30, 45</FIELD2>
		<FIELD3>00, 30</FIELD3>
		<FIELD4>00, 30</FIELD4> 
		<FIELD5>00, 30</FIELD5>
	</ROW>
	<ROW>
		<FIELD1>12</FIELD1>
		<FIELD2>00, 15, 30, 45</FIELD2>
		<FIELD3>00, 30</FIELD3>
		<FIELD4>00, 30</FIELD4> 
		<FIELD5>00, 30</FIELD5>
	</ROW>
	<ROW>
		<FIELD1>13</FIELD1>
		<FIELD2>00, 15, 30, 45</FIELD2>
		<FIELD3>00, 20, 40</FIELD3>
		<FIELD4>00, 30</FIELD4> 
		<FIELD5>00, 30</FIELD5>
	</ROW>
	<ROW>
		<FIELD1>14</FIELD1>
		<FIELD2>00, 15, 30, 45</FIELD2>
		<FIELD3>00, 20, 40</FIELD3>
		<FIELD4>00, 30</FIELD4> 
		<FIELD5>00, 30</FIELD5>
	</ROW>
	<ROW>
		<FIELD1>15</FIELD1>
		<FIELD2>00, 15, 30, 45</FIELD2>
		<FIELD3>00, 20, 40</FIELD3>
		<FIELD4>00, 30</FIELD4> 
		<FIELD5>00, 30</FIELD5>
	</ROW>
	<ROW>
		<FIELD1>16</FIELD1>
		<FIELD2>00, 15, 30, 45</FIELD2>
		<FIELD3>00, 20, 40</FIELD3>
		<FIELD4>00, 30</FIELD4> 
		<FIELD5>00, 30</FIELD5>
	</ROW>
	<ROW>
		<FIELD1>17</FIELD1>
		<FIELD2>00, 15, 30, 45</FIELD2>
		<FIELD3>00, 20, 40</FIELD3>
		<FIELD4>00, 30</FIELD4> 
		<FIELD5>00, 30</FIELD5>
	</ROW>
	<ROW>
		<FIELD1>18</FIELD1>
		<FIELD2>00, 30</FIELD2>
		<FIELD3>00, 30</FIELD3>
		<FIELD4>00, 30</FIELD4> 
		<FIELD5>00, 30</FIELD5>
	</ROW>
	<ROW>
		<FIELD1>19</FIELD1>
		<FIELD2>00, 30</FIELD2>
		<FIELD3>00, 30</FIELD3>
		<FIELD4>00, 30</FIELD4> 
		<FIELD5>00, 30</FIELD5>
	</ROW>
	<ROW>
		<FIELD1>20</FIELD1>
		<FIELD2>00, 30</FIELD2>
		<FIELD3>00, 30</FIELD3>
		<FIELD4>30</FIELD4> 
		<FIELD5>30</FIELD5>
	</ROW>
	<ROW>
		<FIELD1>21</FIELD1>
		<FIELD2>00, 30</FIELD2>
		<FIELD3>00, 30</FIELD3>
		<FIELD4>30</FIELD4> 
		<FIELD5>30</FIELD5>
	</ROW>
	<ROW>
		<FIELD1>22</FIELD1>
		<FIELD2>00, 30</FIELD2>
		<FIELD3>00, 30</FIELD3>
		<FIELD4>30</FIELD4> 
		<FIELD5>30</FIELD5>
	</ROW>
</ROWSET>
